code_analyzer/__init__.py
code_analyzer/code_analyzer.py
code_complexity_analyzer-1.0.0.dist-info/licenses/LICENSE
code_complexity_analyzer-1.0.0.dist-info/METADATA
code_complexity_analyzer-1.0.0.dist-info/WHEEL
code_complexity_analyzer-1.0.0.dist-info/top_level.txt
code_complexity_analyzer-1.0.0.dist-info/RECORD
