Metadata-Version: 2.4
Name: code-complexity-analyzer
Version: 1.0.0
Summary: A comprehensive Python code complexity analyzer
Home-page: https://github.com/yourusername/code-complexity-analyzer
Author: Your Name
Author-email: Your Name <your.email@example.com>
License: MIT
Project-URL: Homepage, https://github.com/yourusername/code-complexity-analyzer
Project-URL: Documentation, https://github.com/yourusername/code-complexity-analyzer#readme
Project-URL: Repository, https://github.com/yourusername/code-complexity-analyzer
Project-URL: Bug Tracker, https://github.com/yourusername/code-complexity-analyzer/issues
Keywords: code,analysis,complexity,metrics,quality
Classifier: Development Status :: 4 - Beta
Classifier: Intended Audience :: Developers
Classifier: License :: OSI Approved :: MIT License
Classifier: Operating System :: OS Independent
Classifier: Programming Language :: Python :: 3
Classifier: Programming Language :: Python :: 3.7
Classifier: Programming Language :: Python :: 3.8
Classifier: Programming Language :: Python :: 3.9
Classifier: Programming Language :: Python :: 3.10
Classifier: Programming Language :: Python :: 3.11
Classifier: Topic :: Software Development :: Quality Assurance
Requires-Python: >=3.7
License-File: LICENSE
Dynamic: author
Dynamic: home-page
Dynamic: license-file
Dynamic: requires-python
